hyapp/__init__.py
hyapp/aio.py
hyapp/alembics.py
hyapp/api.py
hyapp/base.py
hyapp/datetimes.py
hyapp/funcutils.py
hyapp/https.py
hyapp/jsons.py
hyapp/lifetime.py
hyapp/logs.py
hyapp/py.typed
hyapp/pydantics.py
hyapp/pydsettings.py
hyapp/pytests.py
hyapp/traces.py
hyapp-5.9.0.dist-info/METADATA
hyapp-5.9.0.dist-info/WHEEL
hyapp-5.9.0.dist-info/licenses/LICENSE
hyapp-5.9.0.dist-info/RECORD
