Metadata-Version: 2.4
Name: hyapp
Version: 5.9.0
Project-URL: Repository, https://gitlab.com/hoverhell/hyapp
Author-email: hoverhell <hoverhell@gmail.com>
License-Expression: MIT
License-File: LICENSE
Requires-Python: <4,>=3.11
Requires-Dist: aiohttp-retry>=2
Requires-Dist: aiohttp>=3
Requires-Dist: alembic>=1.15
Requires-Dist: coloredlogs>=15
Requires-Dist: fastapi>=0.115
Requires-Dist: frozendict>=2
Requires-Dist: orjson>=3
Requires-Dist: pydantic-settings>=2.9
Requires-Dist: pydantic>=2
Requires-Dist: python-json-logger>=3.3
Requires-Dist: pyyaml>=6
Requires-Dist: starlette>=0.46
